nlp_emotion_analysis_core/__init__.py
nlp_emotion_analysis_core/emotion.py
nlp_emotion_analysis_core/core/__init__.py
nlp_emotion_analysis_core/core/clinical_info/__init__.py
nlp_emotion_analysis_core/core/clinical_info/clinical_info_extractor.py
nlp_emotion_analysis_core/core/emotions/__init__.py
nlp_emotion_analysis_core/core/emotions/create_word_embedding.py
nlp_emotion_analysis_core/core/emotions/emotion_extractor.py
nlp_emotion_analysis_core/core/emotions/emotion_utilities.py
nlp_emotion_analysis_core/core/emotions/word_embedding_query.py
nlp_emotion_analysis_core/core/engagement/__init__.py
nlp_emotion_analysis_core/core/engagement/engagement_metric_extractor.py
nlp_emotion_analysis_core/core/summary/SmartStoplist.txt
nlp_emotion_analysis_core/core/summary/__init__.py
nlp_emotion_analysis_core/core/summary/keyphrase_extractor.py
nlp_emotion_analysis_core/core/summary/rake.py
nlp_emotion_analysis_core/models/clinical_info/physical.pkl
nlp_emotion_analysis_core/models/emotions/emotions_plutchik.pkl
nlp_emotion_analysis_core/models/emotions/intensifier_vocab.pkl
nlp_emotion_analysis_core/models/emotions/intensifier_vocab_v2.pkl
nlp_emotion_analysis_core/models/emotions/negation_vocab.pkl
nlp_emotion_analysis_core/models/emotions/negation_vocab_v2.pkl
nlp_emotion_analysis_core/utils/__init__.py
nlp_emotion_analysis_core/utils/text_processor.py
nlp_emotion_analysis_core-0.0.3.dist-info/LICENSE
nlp_emotion_analysis_core-0.0.3.dist-info/METADATA
nlp_emotion_analysis_core-0.0.3.dist-info/WHEEL
nlp_emotion_analysis_core-0.0.3.dist-info/top_level.txt
nlp_emotion_analysis_core-0.0.3.dist-info/RECORD
