Metadata-Version: 2.1
Name: nlp-emotion-analysis-core
Version: 0.0.3
Summary: Core NLP library for extracting and analysing emotion and group dynamics in a group setting.
Home-page: https://github.com/CDAC-lab/nlp-emotion-analysis-core
Author: Achini
Author-email: achinia@github.com
Project-URL: Bug Tracker, https://github.com/CDAC-lab/nlp-emotion-analysis-core/issues
Classifier: Programming Language :: Python :: 3
Classifier: License :: OSI Approved :: MIT License
Classifier: Operating System :: OS Independent
Requires-Python: >=3.6
License-File: LICENSE
